odoo/addons/mis_builder/README.rst
odoo/addons/mis_builder/__init__.py
odoo/addons/mis_builder/__manifest__.py
odoo/addons/mis_builder/datas/ir_cron.xml
odoo/addons/mis_builder/i18n/ca.po
odoo/addons/mis_builder/i18n/de.po
odoo/addons/mis_builder/i18n/el.po
odoo/addons/mis_builder/i18n/el_GR.po
odoo/addons/mis_builder/i18n/es.po
odoo/addons/mis_builder/i18n/fr.po
odoo/addons/mis_builder/i18n/hr.po
odoo/addons/mis_builder/i18n/it.po
odoo/addons/mis_builder/i18n/mis_builder.pot
odoo/addons/mis_builder/i18n/nl.po
odoo/addons/mis_builder/i18n/nl_NL.po
odoo/addons/mis_builder/i18n/pt.po
odoo/addons/mis_builder/i18n/pt_BR.po
odoo/addons/mis_builder/i18n/sv.po
odoo/addons/mis_builder/i18n/tr.po
odoo/addons/mis_builder/i18n/zh_CN.po
odoo/addons/mis_builder/migrations/18.0.1.3.0/post-migration.py
odoo/addons/mis_builder/models/__init__.py
odoo/addons/mis_builder/models/accounting_none.py
odoo/addons/mis_builder/models/aep.py
odoo/addons/mis_builder/models/aggregate.py
odoo/addons/mis_builder/models/data_error.py
odoo/addons/mis_builder/models/expression_evaluator.py
odoo/addons/mis_builder/models/kpimatrix.py
odoo/addons/mis_builder/models/mis_kpi_data.py
odoo/addons/mis_builder/models/mis_report.py
odoo/addons/mis_builder/models/mis_report_instance.py
odoo/addons/mis_builder/models/mis_report_instance_annotation.py
odoo/addons/mis_builder/models/mis_report_style.py
odoo/addons/mis_builder/models/mis_report_subreport.py
odoo/addons/mis_builder/models/mis_safe_eval.py
odoo/addons/mis_builder/models/prorata_read_group_mixin.py
odoo/addons/mis_builder/models/simple_array.py
odoo/addons/mis_builder/readme/CONTRIBUTORS.md
odoo/addons/mis_builder/readme/DESCRIPTION.md
odoo/addons/mis_builder/readme/DEVELOP.md
odoo/addons/mis_builder/readme/HISTORY.md
odoo/addons/mis_builder/readme/INSTALL.md
odoo/addons/mis_builder/readme/ROADMAP.md
odoo/addons/mis_builder/readme/USAGE.md
odoo/addons/mis_builder/readme/newsfragments/.gitignore
odoo/addons/mis_builder/report/__init__.py
odoo_addon_mis_builder-18.0.1.7.3.dist-info/METADATA
odoo_addon_mis_builder-18.0.1.7.3.dist-info/WHEEL
odoo_addon_mis_builder-18.0.1.7.3.dist-info/top_level.txt
odoo_addon_mis_builder-18.0.1.7.3.dist-info/RECORD
