Metadata-Version: 2.1
Name: odoo-addon-mis_builder
Version: 18.0.1.7.3
Requires-Python: >=3.10
Requires-Dist: odoo-addon-date_range==18.0.*
Requires-Dist: odoo-addon-report_xlsx==18.0.*
Requires-Dist: odoo==18.0.*
Summary: Build 'Management Information System' Reports and Dashboards
Home-page: https://github.com/OCA/mis-builder
License: AGPL-3
Author: ACSONE SA/NV, Odoo Community Association (OCA)
Author-email: support@odoo-community.org
Classifier: Programming Language :: Python
Classifier: Framework :: Odoo
Classifier: Framework :: Odoo :: 18.0
Classifier: License :: OSI Approved :: GNU Affero General Public License v3
Classifier: Development Status :: 5 - Production/Stable
